pisalt-1.2.4.dist-info/METADATA
pisalt-1.2.4.dist-info/WHEEL
pisalt/__init__.py
pisalt/__init__.pyi
pisalt/__internal__.cpython-312-darwin.so
pisalt/classic/__init__.py
pisalt/classic/__init__.pyi
pisalt/classic/encode/__init__.py
pisalt/classic/encode/__init__.pyi
pisalt/classic/encode/__internal__.py
pisalt/classic/encode/__internal__.pyi
pisalt/classic/hash/__init__.py
pisalt/classic/hash/__init__.pyi
pisalt/classic/hash/__internal__.py
pisalt/classic/hash/__internal__.pyi
pisalt/classic/phf/__init__.py
pisalt/classic/phf/__init__.pyi
pisalt/classic/phf/__internal__.py
pisalt/classic/phf/__internal__.pyi
pisalt/quantum/__init__.py
pisalt/quantum/__init__.pyi
pisalt/quantum/dsa/__init__.py
pisalt/quantum/dsa/__init__.pyi
pisalt/quantum/dsa/__internal__.py
pisalt/quantum/dsa/__internal__.pyi
pisalt/quantum/kem/__init__.py
pisalt/quantum/kem/__init__.pyi
pisalt/quantum/kem/__internal__.py
pisalt/quantum/kem/__internal__.pyi
pisalt-1.2.4.dist-info/RECORD
