Metadata-Version: 2.4
Name: pisalt
Version: 1.2.4
Classifier: Programming Language :: Python :: Implementation :: CPython
Classifier: Programming Language :: Python :: Implementation :: PyPy
Classifier: Programming Language :: Rust
Summary: Python Cryptography
Keywords: python,cryptography
Home-Page: https://github.com/1xfalsebit/pisalt
Author: Anonymous <218768726+1xfalsebit@users.noreply.github.com>
Author-email: Anonymous <218768726+1xfalsebit@users.noreply.github.com>
License: Unlicense
Project-URL: Source Code, https://github.com/1xfalsebit/pisalt
